{
	"textures": [
		{
			"image": "pc1-0.png",
			"normalMap": "pc1-0_n.png",
			"format": "RGBA8888",
			"size": {
				"w": 1870,
				"h": 1974
			},
			"scale": 1,
			"frames": [
				{
					"filename": "stairsdown/pc10073.png",
					"rotated": false,
					"trimmed": false,
					"sourceSize": {
						"w": 357,
						"h": 311
					},
					"spriteSourceSize": {
						"x": 0,
						"y": 0,
						"w": 357,
						"h": 311
					},
					"frame": {
						"x": 1,
						"y": 1,
						"w": 357,
						"h": 311
					},
					"anchor": {
						"x": 0.5,
						"y": 1
					}
				},
				{
					"filename": "stairsdown/pc10074.png",
					"rotated": false,
					"trimmed": false,
					"sourceSize": {
						"w": 357,
						"h": 311
					},
					"spriteSourceSize": {
						"x": 0,
						"y": 0,
						"w": 357,
						"h": 311
					},
					"frame": {
						"x": 360,
						"y": 1,
						"w": 357,
						"h": 311
					},
					"anchor": {
						"x": 0.5,
						"y": 1
					}
				},
				{
					"filename": "stairsdown/pc10075.png",
					"rotated": false,
					"trimmed": false,
					"sourceSize": {
						"w": 357,
						"h": 311
					},
					"spriteSourceSize": {
						"x": 0,
						"y": 0,
						"w": 357,
						"h": 311
					},
					"frame": {
						"x": 719,
						"y": 1,
						"w": 357,
						"h": 311
					},
					"anchor": {
						"x": 0.5,
						"y": 1
					}
				},
				{
					"filename": "stairsdown/pc10076.png",
					"rotated": false,
					"trimmed": false,
					"sourceSize": {
						"w": 357,
						"h": 311
					},
					"spriteSourceSize": {
						"x": 0,
						"y": 0,
						"w": 357,
						"h": 311
					},
					"frame": {
						"x": 1078,
						"y": 1,
						"w": 357,
						"h": 311
					},
					"anchor": {
						"x": 0.5,
						"y": 1
					}
				},
				{
					"filename": "stairsdown/pc10077.png",
					"rotated": false,
					"trimmed": false,
					"sourceSize": {
						"w": 357,
						"h": 311
					},
					"spriteSourceSize": {
						"x": 0,
						"y": 0,
						"w": 357,
						"h": 311
					},
					"frame": {
						"x": 1437,
						"y": 1,
						"w": 357,
						"h": 311
					},
					"anchor": {
						"x": 0.5,
						"y": 1
					}
				},
				{
					"filename": "stairsdown/pc10078.png",
					"rotated": false,
					"trimmed": false,
					"sourceSize": {
						"w": 357,
						"h": 311
					},
					"spriteSourceSize": {
						"x": 0,
						"y": 0,
						"w": 357,
						"h": 311
					},
					"frame": {
						"x": 1,
						"y": 314,
						"w": 357,
						"h": 311
					},
					"anchor": {
						"x": 0.5,
						"y": 1
					}
				},
				{
					"filename": "stairsdown/pc10079.png",
					"rotated": false,
					"trimmed": false,
					"sourceSize": {
						"w": 357,
						"h": 311
					},
					"spriteSourceSize": {
						"x": 0,
						"y": 0,
						"w": 357,
						"h": 311
					},
					"frame": {
						"x": 360,
						"y": 314,
						"w": 357,
						"h": 311
					},
					"anchor": {
						"x": 0.5,
						"y": 1
					}
				},
				{
					"filename": "stairsdown/pc10080.png",
					"rotated": false,
					"trimmed": false,
					"sourceSize": {
						"w": 357,
						"h": 311
					},
					"spriteSourceSize": {
						"x": 0,
						"y": 0,
						"w": 357,
						"h": 311
					},
					"frame": {
						"x": 719,
						"y": 314,
						"w": 357,
						"h": 311
					},
					"anchor": {
						"x": 0.5,
						"y": 1
					}
				},
				{
					"filename": "stairsdown/pc10081.png",
					"rotated": false,
					"trimmed": false,
					"sourceSize": {
						"w": 357,
						"h": 311
					},
					"spriteSourceSize": {
						"x": 0,
						"y": 0,
						"w": 357,
						"h": 311
					},
					"frame": {
						"x": 1078,
						"y": 314,
						"w": 357,
						"h": 311
					},
					"anchor": {
						"x": 0.5,
						"y": 1
					}
				},
				{
					"filename": "stairsdown/pc10082.png",
					"rotated": false,
					"trimmed": false,
					"sourceSize": {
						"w": 357,
						"h": 311
					},
					"spriteSourceSize": {
						"x": 0,
						"y": 0,
						"w": 357,
						"h": 311
					},
					"frame": {
						"x": 1437,
						"y": 314,
						"w": 357,
						"h": 311
					},
					"anchor": {
						"x": 0.5,
						"y": 1
					}
				},
				{
					"filename": "stairsdown/pc10083.png",
					"rotated": false,
					"trimmed": false,
					"sourceSize": {
						"w": 357,
						"h": 311
					},
					"spriteSourceSize": {
						"x": 0,
						"y": 0,
						"w": 357,
						"h": 311
					},
					"frame": {
						"x": 1,
						"y": 627,
						"w": 357,
						"h": 311
					},
					"anchor": {
						"x": 0.5,
						"y": 1
					}
				},
				{
					"filename": "jump/pc10054.png",
					"rotated": false,
					"trimmed": false,
					"sourceSize": {
						"w": 372,
						"h": 335
					},
					"spriteSourceSize": {
						"x": 0,
						"y": 0,
						"w": 372,
						"h": 335
					},
					"frame": {
						"x": 360,
						"y": 627,
						"w": 372,
						"h": 335
					},
					"anchor": {
						"x": 0.5,
						"y": 1
					}
				},
				{
					"filename": "jump/pc10055.png",
					"rotated": false,
					"trimmed": false,
					"sourceSize": {
						"w": 372,
						"h": 335
					},
					"spriteSourceSize": {
						"x": 0,
						"y": 0,
						"w": 372,
						"h": 335
					},
					"frame": {
						"x": 734,
						"y": 627,
						"w": 372,
						"h": 335
					},
					"anchor": {
						"x": 0.5,
						"y": 1
					}
				},
				{
					"filename": "jump/pc10056.png",
					"rotated": false,
					"trimmed": false,
					"sourceSize": {
						"w": 372,
						"h": 335
					},
					"spriteSourceSize": {
						"x": 0,
						"y": 0,
						"w": 372,
						"h": 335
					},
					"frame": {
						"x": 1108,
						"y": 627,
						"w": 372,
						"h": 335
					},
					"anchor": {
						"x": 0.5,
						"y": 1
					}
				},
				{
					"filename": "jump/pc10057.png",
					"rotated": false,
					"trimmed": false,
					"sourceSize": {
						"w": 372,
						"h": 335
					},
					"spriteSourceSize": {
						"x": 0,
						"y": 0,
						"w": 372,
						"h": 335
					},
					"frame": {
						"x": 1482,
						"y": 627,
						"w": 372,
						"h": 335
					},
					"anchor": {
						"x": 0.5,
						"y": 1
					}
				},
				{
					"filename": "jump/pc10058.png",
					"rotated": false,
					"trimmed": false,
					"sourceSize": {
						"w": 372,
						"h": 335
					},
					"spriteSourceSize": {
						"x": 0,
						"y": 0,
						"w": 372,
						"h": 335
					},
					"frame": {
						"x": 1,
						"y": 964,
						"w": 372,
						"h": 335
					},
					"anchor": {
						"x": 0.5,
						"y": 1
					}
				},
				{
					"filename": "jump/pc10059.png",
					"rotated": false,
					"trimmed": false,
					"sourceSize": {
						"w": 372,
						"h": 335
					},
					"spriteSourceSize": {
						"x": 0,
						"y": 0,
						"w": 372,
						"h": 335
					},
					"frame": {
						"x": 375,
						"y": 964,
						"w": 372,
						"h": 335
					},
					"anchor": {
						"x": 0.5,
						"y": 1
					}
				},
				{
					"filename": "jump/pc10060.png",
					"rotated": false,
					"trimmed": false,
					"sourceSize": {
						"w": 372,
						"h": 335
					},
					"spriteSourceSize": {
						"x": 0,
						"y": 0,
						"w": 372,
						"h": 335
					},
					"frame": {
						"x": 749,
						"y": 964,
						"w": 372,
						"h": 335
					},
					"anchor": {
						"x": 0.5,
						"y": 1
					}
				},
				{
					"filename": "jump/pc10061.png",
					"rotated": false,
					"trimmed": false,
					"sourceSize": {
						"w": 372,
						"h": 335
					},
					"spriteSourceSize": {
						"x": 0,
						"y": 0,
						"w": 372,
						"h": 335
					},
					"frame": {
						"x": 1123,
						"y": 964,
						"w": 372,
						"h": 335
					},
					"anchor": {
						"x": 0.5,
						"y": 1
					}
				},
				{
					"filename": "jump/pc10062.png",
					"rotated": false,
					"trimmed": false,
					"sourceSize": {
						"w": 372,
						"h": 335
					},
					"spriteSourceSize": {
						"x": 0,
						"y": 0,
						"w": 372,
						"h": 335
					},
					"frame": {
						"x": 1497,
						"y": 964,
						"w": 372,
						"h": 335
					},
					"anchor": {
						"x": 0.5,
						"y": 1
					}
				},
				{
					"filename": "jump/pc10063.png",
					"rotated": false,
					"trimmed": false,
					"sourceSize": {
						"w": 372,
						"h": 335
					},
					"spriteSourceSize": {
						"x": 0,
						"y": 0,
						"w": 372,
						"h": 335
					},
					"frame": {
						"x": 1,
						"y": 1301,
						"w": 372,
						"h": 335
					},
					"anchor": {
						"x": 0.5,
						"y": 1
					}
				},
				{
					"filename": "jump/pc10064.png",
					"rotated": false,
					"trimmed": false,
					"sourceSize": {
						"w": 372,
						"h": 335
					},
					"spriteSourceSize": {
						"x": 0,
						"y": 0,
						"w": 372,
						"h": 335
					},
					"frame": {
						"x": 375,
						"y": 1301,
						"w": 372,
						"h": 335
					},
					"anchor": {
						"x": 0.5,
						"y": 1
					}
				},
				{
					"filename": "jump/pc10065.png",
					"rotated": false,
					"trimmed": false,
					"sourceSize": {
						"w": 372,
						"h": 335
					},
					"spriteSourceSize": {
						"x": 0,
						"y": 0,
						"w": 372,
						"h": 335
					},
					"frame": {
						"x": 749,
						"y": 1301,
						"w": 372,
						"h": 335
					},
					"anchor": {
						"x": 0.5,
						"y": 1
					}
				},
				{
					"filename": "jump/pc10066.png",
					"rotated": false,
					"trimmed": false,
					"sourceSize": {
						"w": 372,
						"h": 335
					},
					"spriteSourceSize": {
						"x": 0,
						"y": 0,
						"w": 372,
						"h": 335
					},
					"frame": {
						"x": 1123,
						"y": 1301,
						"w": 372,
						"h": 335
					},
					"anchor": {
						"x": 0.5,
						"y": 1
					}
				},
				{
					"filename": "jump/pc10067.png",
					"rotated": false,
					"trimmed": false,
					"sourceSize": {
						"w": 372,
						"h": 335
					},
					"spriteSourceSize": {
						"x": 0,
						"y": 0,
						"w": 372,
						"h": 335
					},
					"frame": {
						"x": 1497,
						"y": 1301,
						"w": 372,
						"h": 335
					},
					"anchor": {
						"x": 0.5,
						"y": 1
					}
				},
				{
					"filename": "jump/pc10068.png",
					"rotated": false,
					"trimmed": false,
					"sourceSize": {
						"w": 372,
						"h": 335
					},
					"spriteSourceSize": {
						"x": 0,
						"y": 0,
						"w": 372,
						"h": 335
					},
					"frame": {
						"x": 1,
						"y": 1638,
						"w": 372,
						"h": 335
					},
					"anchor": {
						"x": 0.5,
						"y": 1
					}
				},
				{
					"filename": "jump/pc10069.png",
					"rotated": false,
					"trimmed": false,
					"sourceSize": {
						"w": 372,
						"h": 335
					},
					"spriteSourceSize": {
						"x": 0,
						"y": 0,
						"w": 372,
						"h": 335
					},
					"frame": {
						"x": 375,
						"y": 1638,
						"w": 372,
						"h": 335
					},
					"anchor": {
						"x": 0.5,
						"y": 1
					}
				},
				{
					"filename": "jump/pc10070.png",
					"rotated": false,
					"trimmed": false,
					"sourceSize": {
						"w": 372,
						"h": 335
					},
					"spriteSourceSize": {
						"x": 0,
						"y": 0,
						"w": 372,
						"h": 335
					},
					"frame": {
						"x": 749,
						"y": 1638,
						"w": 372,
						"h": 335
					},
					"anchor": {
						"x": 0.5,
						"y": 1
					}
				},
				{
					"filename": "jump/pc10071.png",
					"rotated": false,
					"trimmed": false,
					"sourceSize": {
						"w": 372,
						"h": 335
					},
					"spriteSourceSize": {
						"x": 0,
						"y": 0,
						"w": 372,
						"h": 335
					},
					"frame": {
						"x": 1123,
						"y": 1638,
						"w": 372,
						"h": 335
					},
					"anchor": {
						"x": 0.5,
						"y": 1
					}
				},
				{
					"filename": "jump/pc10072.png",
					"rotated": false,
					"trimmed": false,
					"sourceSize": {
						"w": 372,
						"h": 335
					},
					"spriteSourceSize": {
						"x": 0,
						"y": 0,
						"w": 372,
						"h": 335
					},
					"frame": {
						"x": 1497,
						"y": 1638,
						"w": 372,
						"h": 335
					},
					"anchor": {
						"x": 0.5,
						"y": 1
					}
				}
			]
		},
		{
			"image": "pc1-1.png",
			"normalMap": "pc1-1_n.png",
			"format": "RGBA8888",
			"size": {
				"w": 1720,
				"h": 1514
			},
			"scale": 1,
			"frames": [
				{
					"filename": "stairsdown/pc10084.png",
					"rotated": false,
					"trimmed": false,
					"sourceSize": {
						"w": 357,
						"h": 311
					},
					"spriteSourceSize": {
						"x": 0,
						"y": 0,
						"w": 357,
						"h": 311
					},
					"frame": {
						"x": 1,
						"y": 1,
						"w": 357,
						"h": 311
					},
					"anchor": {
						"x": 0.5,
						"y": 1
					}
				},
				{
					"filename": "stairsdown/pc10085.png",
					"rotated": false,
					"trimmed": false,
					"sourceSize": {
						"w": 357,
						"h": 311
					},
					"spriteSourceSize": {
						"x": 0,
						"y": 0,
						"w": 357,
						"h": 311
					},
					"frame": {
						"x": 1,
						"y": 314,
						"w": 357,
						"h": 311
					},
					"anchor": {
						"x": 0.5,
						"y": 1
					}
				},
				{
					"filename": "stairsdown/pc10086.png",
					"rotated": false,
					"trimmed": false,
					"sourceSize": {
						"w": 357,
						"h": 311
					},
					"spriteSourceSize": {
						"x": 0,
						"y": 0,
						"w": 357,
						"h": 311
					},
					"frame": {
						"x": 360,
						"y": 1,
						"w": 357,
						"h": 311
					},
					"anchor": {
						"x": 0.5,
						"y": 1
					}
				},
				{
					"filename": "stairsdown/pc10087.png",
					"rotated": false,
					"trimmed": false,
					"sourceSize": {
						"w": 357,
						"h": 311
					},
					"spriteSourceSize": {
						"x": 0,
						"y": 0,
						"w": 357,
						"h": 311
					},
					"frame": {
						"x": 1,
						"y": 627,
						"w": 357,
						"h": 311
					},
					"anchor": {
						"x": 0.5,
						"y": 1
					}
				},
				{
					"filename": "stairsdown/pc10088.png",
					"rotated": false,
					"trimmed": false,
					"sourceSize": {
						"w": 357,
						"h": 311
					},
					"spriteSourceSize": {
						"x": 0,
						"y": 0,
						"w": 357,
						"h": 311
					},
					"frame": {
						"x": 360,
						"y": 314,
						"w": 357,
						"h": 311
					},
					"anchor": {
						"x": 0.5,
						"y": 1
					}
				},
				{
					"filename": "stairsup/pc10112.png",
					"rotated": false,
					"trimmed": false,
					"sourceSize": {
						"w": 332,
						"h": 329
					},
					"spriteSourceSize": {
						"x": 0,
						"y": 0,
						"w": 332,
						"h": 329
					},
					"frame": {
						"x": 719,
						"y": 1,
						"w": 332,
						"h": 329
					},
					"anchor": {
						"x": 0.5,
						"y": 1
					}
				},
				{
					"filename": "stairsup/pc10113.png",
					"rotated": false,
					"trimmed": false,
					"sourceSize": {
						"w": 332,
						"h": 329
					},
					"spriteSourceSize": {
						"x": 0,
						"y": 0,
						"w": 332,
						"h": 329
					},
					"frame": {
						"x": 1,
						"y": 940,
						"w": 332,
						"h": 329
					},
					"anchor": {
						"x": 0.5,
						"y": 1
					}
				},
				{
					"filename": "stairsup/pc10114.png",
					"rotated": false,
					"trimmed": false,
					"sourceSize": {
						"w": 332,
						"h": 329
					},
					"spriteSourceSize": {
						"x": 0,
						"y": 0,
						"w": 332,
						"h": 329
					},
					"frame": {
						"x": 1053,
						"y": 1,
						"w": 332,
						"h": 329
					},
					"anchor": {
						"x": 0.5,
						"y": 1
					}
				},
				{
					"filename": "stairsup/pc10115.png",
					"rotated": false,
					"trimmed": false,
					"sourceSize": {
						"w": 332,
						"h": 329
					},
					"spriteSourceSize": {
						"x": 0,
						"y": 0,
						"w": 332,
						"h": 329
					},
					"frame": {
						"x": 1387,
						"y": 1,
						"w": 332,
						"h": 329
					},
					"anchor": {
						"x": 0.5,
						"y": 1
					}
				},
				{
					"filename": "idle/pc10034.png",
					"rotated": false,
					"trimmed": false,
					"sourceSize": {
						"w": 337,
						"h": 293
					},
					"spriteSourceSize": {
						"x": 0,
						"y": 0,
						"w": 337,
						"h": 293
					},
					"frame": {
						"x": 360,
						"y": 627,
						"w": 337,
						"h": 293
					},
					"anchor": {
						"x": 0.5,
						"y": 1
					}
				},
				{
					"filename": "idle/pc10035.png",
					"rotated": false,
					"trimmed": false,
					"sourceSize": {
						"w": 337,
						"h": 293
					},
					"spriteSourceSize": {
						"x": 0,
						"y": 0,
						"w": 337,
						"h": 293
					},
					"frame": {
						"x": 719,
						"y": 332,
						"w": 337,
						"h": 293
					},
					"anchor": {
						"x": 0.5,
						"y": 1
					}
				},
				{
					"filename": "idle/pc10036.png",
					"rotated": false,
					"trimmed": false,
					"sourceSize": {
						"w": 337,
						"h": 293
					},
					"spriteSourceSize": {
						"x": 0,
						"y": 0,
						"w": 337,
						"h": 293
					},
					"frame": {
						"x": 699,
						"y": 627,
						"w": 337,
						"h": 293
					},
					"anchor": {
						"x": 0.5,
						"y": 1
					}
				},
				{
					"filename": "idle/pc10037.png",
					"rotated": false,
					"trimmed": false,
					"sourceSize": {
						"w": 337,
						"h": 293
					},
					"spriteSourceSize": {
						"x": 0,
						"y": 0,
						"w": 337,
						"h": 293
					},
					"frame": {
						"x": 1058,
						"y": 332,
						"w": 337,
						"h": 293
					},
					"anchor": {
						"x": 0.5,
						"y": 1
					}
				},
				{
					"filename": "idle/pc10038.png",
					"rotated": false,
					"trimmed": false,
					"sourceSize": {
						"w": 337,
						"h": 293
					},
					"spriteSourceSize": {
						"x": 0,
						"y": 0,
						"w": 337,
						"h": 293
					},
					"frame": {
						"x": 1038,
						"y": 627,
						"w": 337,
						"h": 293
					},
					"anchor": {
						"x": 0.5,
						"y": 1
					}
				},
				{
					"filename": "hide/pc10043.png",
					"rotated": false,
					"trimmed": false,
					"sourceSize": {
						"w": 312,
						"h": 242
					},
					"spriteSourceSize": {
						"x": 0,
						"y": 0,
						"w": 312,
						"h": 242
					},
					"frame": {
						"x": 1,
						"y": 1271,
						"w": 312,
						"h": 242
					},
					"anchor": {
						"x": 0.5,
						"y": 1
					}
				},
				{
					"filename": "hide/pc10044.png",
					"rotated": false,
					"trimmed": false,
					"sourceSize": {
						"w": 312,
						"h": 242
					},
					"spriteSourceSize": {
						"x": 0,
						"y": 0,
						"w": 312,
						"h": 242
					},
					"frame": {
						"x": 1397,
						"y": 332,
						"w": 312,
						"h": 242
					},
					"anchor": {
						"x": 0.5,
						"y": 1
					}
				},
				{
					"filename": "hide/pc10045.png",
					"rotated": false,
					"trimmed": false,
					"sourceSize": {
						"w": 312,
						"h": 242
					},
					"spriteSourceSize": {
						"x": 0,
						"y": 0,
						"w": 312,
						"h": 242
					},
					"frame": {
						"x": 1397,
						"y": 576,
						"w": 312,
						"h": 242
					},
					"anchor": {
						"x": 0.5,
						"y": 1
					}
				},
				{
					"filename": "idle/pc10039.png",
					"rotated": false,
					"trimmed": false,
					"sourceSize": {
						"w": 337,
						"h": 293
					},
					"spriteSourceSize": {
						"x": 0,
						"y": 0,
						"w": 337,
						"h": 293
					},
					"frame": {
						"x": 1377,
						"y": 820,
						"w": 337,
						"h": 293
					},
					"anchor": {
						"x": 0.5,
						"y": 1
					}
				},
				{
					"filename": "walk/pc10028.png",
					"rotated": false,
					"trimmed": false,
					"sourceSize": {
						"w": 337,
						"h": 293
					},
					"spriteSourceSize": {
						"x": 0,
						"y": 0,
						"w": 337,
						"h": 293
					},
					"frame": {
						"x": 360,
						"y": 922,
						"w": 337,
						"h": 293
					},
					"anchor": {
						"x": 0.5,
						"y": 1
					}
				},
				{
					"filename": "walk/pc10029.png",
					"rotated": false,
					"trimmed": false,
					"sourceSize": {
						"w": 337,
						"h": 293
					},
					"spriteSourceSize": {
						"x": 0,
						"y": 0,
						"w": 337,
						"h": 293
					},
					"frame": {
						"x": 699,
						"y": 922,
						"w": 337,
						"h": 293
					},
					"anchor": {
						"x": 0.5,
						"y": 1
					}
				},
				{
					"filename": "walk/pc10030.png",
					"rotated": false,
					"trimmed": false,
					"sourceSize": {
						"w": 337,
						"h": 293
					},
					"spriteSourceSize": {
						"x": 0,
						"y": 0,
						"w": 337,
						"h": 293
					},
					"frame": {
						"x": 1038,
						"y": 922,
						"w": 337,
						"h": 293
					},
					"anchor": {
						"x": 0.5,
						"y": 1
					}
				},
				{
					"filename": "walk/pc10031.png",
					"rotated": false,
					"trimmed": false,
					"sourceSize": {
						"w": 337,
						"h": 293
					},
					"spriteSourceSize": {
						"x": 0,
						"y": 0,
						"w": 337,
						"h": 293
					},
					"frame": {
						"x": 1377,
						"y": 1115,
						"w": 337,
						"h": 293
					},
					"anchor": {
						"x": 0.5,
						"y": 1
					}
				},
				{
					"filename": "walk/pc10032.png",
					"rotated": false,
					"trimmed": false,
					"sourceSize": {
						"w": 337,
						"h": 293
					},
					"spriteSourceSize": {
						"x": 0,
						"y": 0,
						"w": 337,
						"h": 293
					},
					"frame": {
						"x": 335,
						"y": 1217,
						"w": 337,
						"h": 293
					},
					"anchor": {
						"x": 0.5,
						"y": 1
					}
				},
				{
					"filename": "walk/pc10033.png",
					"rotated": false,
					"trimmed": false,
					"sourceSize": {
						"w": 337,
						"h": 293
					},
					"spriteSourceSize": {
						"x": 0,
						"y": 0,
						"w": 337,
						"h": 293
					},
					"frame": {
						"x": 674,
						"y": 1217,
						"w": 337,
						"h": 293
					},
					"anchor": {
						"x": 0.5,
						"y": 1
					}
				},
				{
					"filename": "hide/pc10046.png",
					"rotated": false,
					"trimmed": false,
					"sourceSize": {
						"w": 312,
						"h": 242
					},
					"spriteSourceSize": {
						"x": 0,
						"y": 0,
						"w": 312,
						"h": 242
					},
					"frame": {
						"x": 1013,
						"y": 1217,
						"w": 312,
						"h": 242
					},
					"anchor": {
						"x": 0.5,
						"y": 1
					}
				}
			]
		},
		{
			"image": "pc1-2.png",
			"normalMap": "pc1-2_n.png",
			"format": "RGBA8888",
			"size": {
				"w": 2029,
				"h": 1219
			},
			"scale": 1,
			"frames": [
				{
					"filename": "hide/pc10048.png",
					"rotated": false,
					"trimmed": false,
					"sourceSize": {
						"w": 312,
						"h": 242
					},
					"spriteSourceSize": {
						"x": 0,
						"y": 0,
						"w": 312,
						"h": 242
					},
					"frame": {
						"x": 1,
						"y": 1,
						"w": 312,
						"h": 242
					},
					"anchor": {
						"x": 0.5,
						"y": 1
					}
				},
				{
					"filename": "hide/pc10049.png",
					"rotated": false,
					"trimmed": false,
					"sourceSize": {
						"w": 312,
						"h": 242
					},
					"spriteSourceSize": {
						"x": 0,
						"y": 0,
						"w": 312,
						"h": 242
					},
					"frame": {
						"x": 315,
						"y": 1,
						"w": 312,
						"h": 242
					},
					"anchor": {
						"x": 0.5,
						"y": 1
					}
				},
				{
					"filename": "hide/pc10050.png",
					"rotated": false,
					"trimmed": false,
					"sourceSize": {
						"w": 312,
						"h": 242
					},
					"spriteSourceSize": {
						"x": 0,
						"y": 0,
						"w": 312,
						"h": 242
					},
					"frame": {
						"x": 629,
						"y": 1,
						"w": 312,
						"h": 242
					},
					"anchor": {
						"x": 0.5,
						"y": 1
					}
				},
				{
					"filename": "hide/pc10051.png",
					"rotated": false,
					"trimmed": false,
					"sourceSize": {
						"w": 312,
						"h": 242
					},
					"spriteSourceSize": {
						"x": 0,
						"y": 0,
						"w": 312,
						"h": 242
					},
					"frame": {
						"x": 943,
						"y": 1,
						"w": 312,
						"h": 242
					},
					"anchor": {
						"x": 0.5,
						"y": 1
					}
				},
				{
					"filename": "hide/pc10052.png",
					"rotated": false,
					"trimmed": false,
					"sourceSize": {
						"w": 312,
						"h": 242
					},
					"spriteSourceSize": {
						"x": 0,
						"y": 0,
						"w": 312,
						"h": 242
					},
					"frame": {
						"x": 1257,
						"y": 1,
						"w": 312,
						"h": 242
					},
					"anchor": {
						"x": 0.5,
						"y": 1
					}
				},
				{
					"filename": "hide/pc10053.png",
					"rotated": false,
					"trimmed": false,
					"sourceSize": {
						"w": 312,
						"h": 242
					},
					"spriteSourceSize": {
						"x": 0,
						"y": 0,
						"w": 312,
						"h": 242
					},
					"frame": {
						"x": 1571,
						"y": 1,
						"w": 312,
						"h": 242
					},
					"anchor": {
						"x": 0.5,
						"y": 1
					}
				},
				{
					"filename": "idle/pc10040.png",
					"rotated": false,
					"trimmed": false,
					"sourceSize": {
						"w": 337,
						"h": 293
					},
					"spriteSourceSize": {
						"x": 0,
						"y": 0,
						"w": 337,
						"h": 293
					},
					"frame": {
						"x": 1,
						"y": 245,
						"w": 337,
						"h": 293
					},
					"anchor": {
						"x": 0.5,
						"y": 1
					}
				},
				{
					"filename": "idle/pc10041.png",
					"rotated": false,
					"trimmed": false,
					"sourceSize": {
						"w": 337,
						"h": 293
					},
					"spriteSourceSize": {
						"x": 0,
						"y": 0,
						"w": 337,
						"h": 293
					},
					"frame": {
						"x": 340,
						"y": 245,
						"w": 337,
						"h": 293
					},
					"anchor": {
						"x": 0.5,
						"y": 1
					}
				},
				{
					"filename": "idle/pc10042.png",
					"rotated": false,
					"trimmed": false,
					"sourceSize": {
						"w": 337,
						"h": 293
					},
					"spriteSourceSize": {
						"x": 0,
						"y": 0,
						"w": 337,
						"h": 293
					},
					"frame": {
						"x": 679,
						"y": 245,
						"w": 337,
						"h": 293
					},
					"anchor": {
						"x": 0.5,
						"y": 1
					}
				},
				{
					"filename": "walk/pc10001.png",
					"rotated": false,
					"trimmed": false,
					"sourceSize": {
						"w": 337,
						"h": 293
					},
					"spriteSourceSize": {
						"x": 0,
						"y": 0,
						"w": 337,
						"h": 293
					},
					"frame": {
						"x": 1018,
						"y": 245,
						"w": 337,
						"h": 293
					},
					"anchor": {
						"x": 0.5,
						"y": 1
					}
				},
				{
					"filename": "walk/pc10002.png",
					"rotated": false,
					"trimmed": false,
					"sourceSize": {
						"w": 337,
						"h": 293
					},
					"spriteSourceSize": {
						"x": 0,
						"y": 0,
						"w": 337,
						"h": 293
					},
					"frame": {
						"x": 1357,
						"y": 245,
						"w": 337,
						"h": 293
					},
					"anchor": {
						"x": 0.5,
						"y": 1
					}
				},
				{
					"filename": "stairsup/pc10100.png",
					"rotated": false,
					"trimmed": false,
					"sourceSize": {
						"w": 332,
						"h": 329
					},
					"spriteSourceSize": {
						"x": 0,
						"y": 0,
						"w": 332,
						"h": 329
					},
					"frame": {
						"x": 1696,
						"y": 245,
						"w": 332,
						"h": 329
					},
					"anchor": {
						"x": 0.5,
						"y": 1
					}
				},
				{
					"filename": "stairsdown/pc10089.png",
					"rotated": false,
					"trimmed": false,
					"sourceSize": {
						"w": 357,
						"h": 311
					},
					"spriteSourceSize": {
						"x": 0,
						"y": 0,
						"w": 357,
						"h": 311
					},
					"frame": {
						"x": 1,
						"y": 540,
						"w": 357,
						"h": 311
					},
					"anchor": {
						"x": 0.5,
						"y": 1
					}
				},
				{
					"filename": "stairsdown/pc10090.png",
					"rotated": false,
					"trimmed": false,
					"sourceSize": {
						"w": 357,
						"h": 311
					},
					"spriteSourceSize": {
						"x": 0,
						"y": 0,
						"w": 357,
						"h": 311
					},
					"frame": {
						"x": 360,
						"y": 540,
						"w": 357,
						"h": 311
					},
					"anchor": {
						"x": 0.5,
						"y": 1
					}
				},
				{
					"filename": "stairsdown/pc10091.png",
					"rotated": false,
					"trimmed": false,
					"sourceSize": {
						"w": 357,
						"h": 311
					},
					"spriteSourceSize": {
						"x": 0,
						"y": 0,
						"w": 357,
						"h": 311
					},
					"frame": {
						"x": 719,
						"y": 540,
						"w": 357,
						"h": 311
					},
					"anchor": {
						"x": 0.5,
						"y": 1
					}
				},
				{
					"filename": "stairsdown/pc10092.png",
					"rotated": false,
					"trimmed": false,
					"sourceSize": {
						"w": 357,
						"h": 311
					},
					"spriteSourceSize": {
						"x": 0,
						"y": 0,
						"w": 357,
						"h": 311
					},
					"frame": {
						"x": 1078,
						"y": 540,
						"w": 357,
						"h": 311
					},
					"anchor": {
						"x": 0.5,
						"y": 1
					}
				},
				{
					"filename": "stairsdown/pc10093.png",
					"rotated": false,
					"trimmed": false,
					"sourceSize": {
						"w": 357,
						"h": 311
					},
					"spriteSourceSize": {
						"x": 0,
						"y": 0,
						"w": 357,
						"h": 311
					},
					"frame": {
						"x": 1437,
						"y": 576,
						"w": 357,
						"h": 311
					},
					"anchor": {
						"x": 0.5,
						"y": 1
					}
				},
				{
					"filename": "stairsup/pc10106.png",
					"rotated": false,
					"trimmed": false,
					"sourceSize": {
						"w": 332,
						"h": 329
					},
					"spriteSourceSize": {
						"x": 0,
						"y": 0,
						"w": 332,
						"h": 329
					},
					"frame": {
						"x": 1,
						"y": 853,
						"w": 332,
						"h": 329
					},
					"anchor": {
						"x": 0.5,
						"y": 1
					}
				},
				{
					"filename": "stairsup/pc10107.png",
					"rotated": false,
					"trimmed": false,
					"sourceSize": {
						"w": 332,
						"h": 329
					},
					"spriteSourceSize": {
						"x": 0,
						"y": 0,
						"w": 332,
						"h": 329
					},
					"frame": {
						"x": 335,
						"y": 853,
						"w": 332,
						"h": 329
					},
					"anchor": {
						"x": 0.5,
						"y": 1
					}
				},
				{
					"filename": "stairsup/pc10108.png",
					"rotated": false,
					"trimmed": false,
					"sourceSize": {
						"w": 332,
						"h": 329
					},
					"spriteSourceSize": {
						"x": 0,
						"y": 0,
						"w": 332,
						"h": 329
					},
					"frame": {
						"x": 669,
						"y": 853,
						"w": 332,
						"h": 329
					},
					"anchor": {
						"x": 0.5,
						"y": 1
					}
				},
				{
					"filename": "stairsup/pc10109.png",
					"rotated": false,
					"trimmed": false,
					"sourceSize": {
						"w": 332,
						"h": 329
					},
					"spriteSourceSize": {
						"x": 0,
						"y": 0,
						"w": 332,
						"h": 329
					},
					"frame": {
						"x": 1003,
						"y": 853,
						"w": 332,
						"h": 329
					},
					"anchor": {
						"x": 0.5,
						"y": 1
					}
				},
				{
					"filename": "stairsup/pc10110.png",
					"rotated": false,
					"trimmed": false,
					"sourceSize": {
						"w": 332,
						"h": 329
					},
					"spriteSourceSize": {
						"x": 0,
						"y": 0,
						"w": 332,
						"h": 329
					},
					"frame": {
						"x": 1337,
						"y": 889,
						"w": 332,
						"h": 329
					},
					"anchor": {
						"x": 0.5,
						"y": 1
					}
				},
				{
					"filename": "stairsup/pc10111.png",
					"rotated": false,
					"trimmed": false,
					"sourceSize": {
						"w": 332,
						"h": 329
					},
					"spriteSourceSize": {
						"x": 0,
						"y": 0,
						"w": 332,
						"h": 329
					},
					"frame": {
						"x": 1671,
						"y": 889,
						"w": 332,
						"h": 329
					},
					"anchor": {
						"x": 0.5,
						"y": 1
					}
				}
			]
		},
		{
			"image": "pc1-3.png",
			"normalMap": "pc1-3_n.png",
			"format": "RGBA8888",
			"size": {
				"w": 2029,
				"h": 2032
			},
			"scale": 1,
			"frames": [
				{
					"filename": "stairsdown/pc10094.png",
					"rotated": false,
					"trimmed": false,
					"sourceSize": {
						"w": 357,
						"h": 311
					},
					"spriteSourceSize": {
						"x": 0,
						"y": 0,
						"w": 357,
						"h": 311
					},
					"frame": {
						"x": 1,
						"y": 1,
						"w": 357,
						"h": 311
					},
					"anchor": {
						"x": 0.5,
						"y": 1
					}
				},
				{
					"filename": "stairsup/pc10095.png",
					"rotated": false,
					"trimmed": false,
					"sourceSize": {
						"w": 332,
						"h": 329
					},
					"spriteSourceSize": {
						"x": 0,
						"y": 0,
						"w": 332,
						"h": 329
					},
					"frame": {
						"x": 360,
						"y": 1,
						"w": 332,
						"h": 329
					},
					"anchor": {
						"x": 0.5,
						"y": 1
					}
				},
				{
					"filename": "stairsup/pc10096.png",
					"rotated": false,
					"trimmed": false,
					"sourceSize": {
						"w": 332,
						"h": 329
					},
					"spriteSourceSize": {
						"x": 0,
						"y": 0,
						"w": 332,
						"h": 329
					},
					"frame": {
						"x": 694,
						"y": 1,
						"w": 332,
						"h": 329
					},
					"anchor": {
						"x": 0.5,
						"y": 1
					}
				},
				{
					"filename": "stairsup/pc10097.png",
					"rotated": false,
					"trimmed": false,
					"sourceSize": {
						"w": 332,
						"h": 329
					},
					"spriteSourceSize": {
						"x": 0,
						"y": 0,
						"w": 332,
						"h": 329
					},
					"frame": {
						"x": 1028,
						"y": 1,
						"w": 332,
						"h": 329
					},
					"anchor": {
						"x": 0.5,
						"y": 1
					}
				},
				{
					"filename": "stairsup/pc10098.png",
					"rotated": false,
					"trimmed": false,
					"sourceSize": {
						"w": 332,
						"h": 329
					},
					"spriteSourceSize": {
						"x": 0,
						"y": 0,
						"w": 332,
						"h": 329
					},
					"frame": {
						"x": 1362,
						"y": 1,
						"w": 332,
						"h": 329
					},
					"anchor": {
						"x": 0.5,
						"y": 1
					}
				},
				{
					"filename": "stairsup/pc10099.png",
					"rotated": false,
					"trimmed": false,
					"sourceSize": {
						"w": 332,
						"h": 329
					},
					"spriteSourceSize": {
						"x": 0,
						"y": 0,
						"w": 332,
						"h": 329
					},
					"frame": {
						"x": 1696,
						"y": 1,
						"w": 332,
						"h": 329
					},
					"anchor": {
						"x": 0.5,
						"y": 1
					}
				},
				{
					"filename": "walk/pc10003.png",
					"rotated": false,
					"trimmed": false,
					"sourceSize": {
						"w": 337,
						"h": 293
					},
					"spriteSourceSize": {
						"x": 0,
						"y": 0,
						"w": 337,
						"h": 293
					},
					"frame": {
						"x": 1,
						"y": 314,
						"w": 337,
						"h": 293
					},
					"anchor": {
						"x": 0.5,
						"y": 1
					}
				},
				{
					"filename": "walk/pc10004.png",
					"rotated": false,
					"trimmed": false,
					"sourceSize": {
						"w": 337,
						"h": 293
					},
					"spriteSourceSize": {
						"x": 0,
						"y": 0,
						"w": 337,
						"h": 293
					},
					"frame": {
						"x": 340,
						"y": 332,
						"w": 337,
						"h": 293
					},
					"anchor": {
						"x": 0.5,
						"y": 1
					}
				},
				{
					"filename": "walk/pc10005.png",
					"rotated": false,
					"trimmed": false,
					"sourceSize": {
						"w": 337,
						"h": 293
					},
					"spriteSourceSize": {
						"x": 0,
						"y": 0,
						"w": 337,
						"h": 293
					},
					"frame": {
						"x": 679,
						"y": 332,
						"w": 337,
						"h": 293
					},
					"anchor": {
						"x": 0.5,
						"y": 1
					}
				},
				{
					"filename": "walk/pc10006.png",
					"rotated": false,
					"trimmed": false,
					"sourceSize": {
						"w": 337,
						"h": 293
					},
					"spriteSourceSize": {
						"x": 0,
						"y": 0,
						"w": 337,
						"h": 293
					},
					"frame": {
						"x": 1018,
						"y": 332,
						"w": 337,
						"h": 293
					},
					"anchor": {
						"x": 0.5,
						"y": 1
					}
				},
				{
					"filename": "walk/pc10007.png",
					"rotated": false,
					"trimmed": false,
					"sourceSize": {
						"w": 337,
						"h": 293
					},
					"spriteSourceSize": {
						"x": 0,
						"y": 0,
						"w": 337,
						"h": 293
					},
					"frame": {
						"x": 1357,
						"y": 332,
						"w": 337,
						"h": 293
					},
					"anchor": {
						"x": 0.5,
						"y": 1
					}
				},
				{
					"filename": "stairsup/pc10101.png",
					"rotated": false,
					"trimmed": false,
					"sourceSize": {
						"w": 332,
						"h": 329
					},
					"spriteSourceSize": {
						"x": 0,
						"y": 0,
						"w": 332,
						"h": 329
					},
					"frame": {
						"x": 1696,
						"y": 332,
						"w": 332,
						"h": 329
					},
					"anchor": {
						"x": 0.5,
						"y": 1
					}
				},
				{
					"filename": "walk/pc10008.png",
					"rotated": false,
					"trimmed": false,
					"sourceSize": {
						"w": 337,
						"h": 293
					},
					"spriteSourceSize": {
						"x": 0,
						"y": 0,
						"w": 337,
						"h": 293
					},
					"frame": {
						"x": 1,
						"y": 609,
						"w": 337,
						"h": 293
					},
					"anchor": {
						"x": 0.5,
						"y": 1
					}
				},
				{
					"filename": "walk/pc10009.png",
					"rotated": false,
					"trimmed": false,
					"sourceSize": {
						"w": 337,
						"h": 293
					},
					"spriteSourceSize": {
						"x": 0,
						"y": 0,
						"w": 337,
						"h": 293
					},
					"frame": {
						"x": 340,
						"y": 627,
						"w": 337,
						"h": 293
					},
					"anchor": {
						"x": 0.5,
						"y": 1
					}
				},
				{
					"filename": "walk/pc10010.png",
					"rotated": false,
					"trimmed": false,
					"sourceSize": {
						"w": 337,
						"h": 293
					},
					"spriteSourceSize": {
						"x": 0,
						"y": 0,
						"w": 337,
						"h": 293
					},
					"frame": {
						"x": 679,
						"y": 627,
						"w": 337,
						"h": 293
					},
					"anchor": {
						"x": 0.5,
						"y": 1
					}
				},
				{
					"filename": "walk/pc10011.png",
					"rotated": false,
					"trimmed": false,
					"sourceSize": {
						"w": 337,
						"h": 293
					},
					"spriteSourceSize": {
						"x": 0,
						"y": 0,
						"w": 337,
						"h": 293
					},
					"frame": {
						"x": 1018,
						"y": 627,
						"w": 337,
						"h": 293
					},
					"anchor": {
						"x": 0.5,
						"y": 1
					}
				},
				{
					"filename": "walk/pc10012.png",
					"rotated": false,
					"trimmed": false,
					"sourceSize": {
						"w": 337,
						"h": 293
					},
					"spriteSourceSize": {
						"x": 0,
						"y": 0,
						"w": 337,
						"h": 293
					},
					"frame": {
						"x": 1357,
						"y": 627,
						"w": 337,
						"h": 293
					},
					"anchor": {
						"x": 0.5,
						"y": 1
					}
				},
				{
					"filename": "stairsup/pc10102.png",
					"rotated": false,
					"trimmed": false,
					"sourceSize": {
						"w": 332,
						"h": 329
					},
					"spriteSourceSize": {
						"x": 0,
						"y": 0,
						"w": 332,
						"h": 329
					},
					"frame": {
						"x": 1696,
						"y": 663,
						"w": 332,
						"h": 329
					},
					"anchor": {
						"x": 0.5,
						"y": 1
					}
				},
				{
					"filename": "walk/pc10013.png",
					"rotated": false,
					"trimmed": false,
					"sourceSize": {
						"w": 337,
						"h": 293
					},
					"spriteSourceSize": {
						"x": 0,
						"y": 0,
						"w": 337,
						"h": 293
					},
					"frame": {
						"x": 1,
						"y": 904,
						"w": 337,
						"h": 293
					},
					"anchor": {
						"x": 0.5,
						"y": 1
					}
				},
				{
					"filename": "walk/pc10014.png",
					"rotated": false,
					"trimmed": false,
					"sourceSize": {
						"w": 337,
						"h": 293
					},
					"spriteSourceSize": {
						"x": 0,
						"y": 0,
						"w": 337,
						"h": 293
					},
					"frame": {
						"x": 340,
						"y": 922,
						"w": 337,
						"h": 293
					},
					"anchor": {
						"x": 0.5,
						"y": 1
					}
				},
				{
					"filename": "walk/pc10015.png",
					"rotated": false,
					"trimmed": false,
					"sourceSize": {
						"w": 337,
						"h": 293
					},
					"spriteSourceSize": {
						"x": 0,
						"y": 0,
						"w": 337,
						"h": 293
					},
					"frame": {
						"x": 679,
						"y": 922,
						"w": 337,
						"h": 293
					},
					"anchor": {
						"x": 0.5,
						"y": 1
					}
				},
				{
					"filename": "walk/pc10016.png",
					"rotated": false,
					"trimmed": false,
					"sourceSize": {
						"w": 337,
						"h": 293
					},
					"spriteSourceSize": {
						"x": 0,
						"y": 0,
						"w": 337,
						"h": 293
					},
					"frame": {
						"x": 1018,
						"y": 922,
						"w": 337,
						"h": 293
					},
					"anchor": {
						"x": 0.5,
						"y": 1
					}
				},
				{
					"filename": "walk/pc10017.png",
					"rotated": false,
					"trimmed": false,
					"sourceSize": {
						"w": 337,
						"h": 293
					},
					"spriteSourceSize": {
						"x": 0,
						"y": 0,
						"w": 337,
						"h": 293
					},
					"frame": {
						"x": 1357,
						"y": 922,
						"w": 337,
						"h": 293
					},
					"anchor": {
						"x": 0.5,
						"y": 1
					}
				},
				{
					"filename": "stairsup/pc10103.png",
					"rotated": false,
					"trimmed": false,
					"sourceSize": {
						"w": 332,
						"h": 329
					},
					"spriteSourceSize": {
						"x": 0,
						"y": 0,
						"w": 332,
						"h": 329
					},
					"frame": {
						"x": 1696,
						"y": 994,
						"w": 332,
						"h": 329
					},
					"anchor": {
						"x": 0.5,
						"y": 1
					}
				},
				{
					"filename": "walk/pc10018.png",
					"rotated": false,
					"trimmed": false,
					"sourceSize": {
						"w": 337,
						"h": 293
					},
					"spriteSourceSize": {
						"x": 0,
						"y": 0,
						"w": 337,
						"h": 293
					},
					"frame": {
						"x": 1,
						"y": 1199,
						"w": 337,
						"h": 293
					},
					"anchor": {
						"x": 0.5,
						"y": 1
					}
				},
				{
					"filename": "walk/pc10019.png",
					"rotated": false,
					"trimmed": false,
					"sourceSize": {
						"w": 337,
						"h": 293
					},
					"spriteSourceSize": {
						"x": 0,
						"y": 0,
						"w": 337,
						"h": 293
					},
					"frame": {
						"x": 340,
						"y": 1217,
						"w": 337,
						"h": 293
					},
					"anchor": {
						"x": 0.5,
						"y": 1
					}
				},
				{
					"filename": "walk/pc10020.png",
					"rotated": false,
					"trimmed": false,
					"sourceSize": {
						"w": 337,
						"h": 293
					},
					"spriteSourceSize": {
						"x": 0,
						"y": 0,
						"w": 337,
						"h": 293
					},
					"frame": {
						"x": 679,
						"y": 1217,
						"w": 337,
						"h": 293
					},
					"anchor": {
						"x": 0.5,
						"y": 1
					}
				},
				{
					"filename": "walk/pc10021.png",
					"rotated": false,
					"trimmed": false,
					"sourceSize": {
						"w": 337,
						"h": 293
					},
					"spriteSourceSize": {
						"x": 0,
						"y": 0,
						"w": 337,
						"h": 293
					},
					"frame": {
						"x": 1018,
						"y": 1217,
						"w": 337,
						"h": 293
					},
					"anchor": {
						"x": 0.5,
						"y": 1
					}
				},
				{
					"filename": "walk/pc10022.png",
					"rotated": false,
					"trimmed": false,
					"sourceSize": {
						"w": 337,
						"h": 293
					},
					"spriteSourceSize": {
						"x": 0,
						"y": 0,
						"w": 337,
						"h": 293
					},
					"frame": {
						"x": 1357,
						"y": 1217,
						"w": 337,
						"h": 293
					},
					"anchor": {
						"x": 0.5,
						"y": 1
					}
				},
				{
					"filename": "stairsup/pc10104.png",
					"rotated": false,
					"trimmed": false,
					"sourceSize": {
						"w": 332,
						"h": 329
					},
					"spriteSourceSize": {
						"x": 0,
						"y": 0,
						"w": 332,
						"h": 329
					},
					"frame": {
						"x": 1696,
						"y": 1325,
						"w": 332,
						"h": 329
					},
					"anchor": {
						"x": 0.5,
						"y": 1
					}
				},
				{
					"filename": "walk/pc10023.png",
					"rotated": false,
					"trimmed": false,
					"sourceSize": {
						"w": 337,
						"h": 293
					},
					"spriteSourceSize": {
						"x": 0,
						"y": 0,
						"w": 337,
						"h": 293
					},
					"frame": {
						"x": 1,
						"y": 1494,
						"w": 337,
						"h": 293
					},
					"anchor": {
						"x": 0.5,
						"y": 1
					}
				},
				{
					"filename": "walk/pc10024.png",
					"rotated": false,
					"trimmed": false,
					"sourceSize": {
						"w": 337,
						"h": 293
					},
					"spriteSourceSize": {
						"x": 0,
						"y": 0,
						"w": 337,
						"h": 293
					},
					"frame": {
						"x": 340,
						"y": 1512,
						"w": 337,
						"h": 293
					},
					"anchor": {
						"x": 0.5,
						"y": 1
					}
				},
				{
					"filename": "walk/pc10025.png",
					"rotated": false,
					"trimmed": false,
					"sourceSize": {
						"w": 337,
						"h": 293
					},
					"spriteSourceSize": {
						"x": 0,
						"y": 0,
						"w": 337,
						"h": 293
					},
					"frame": {
						"x": 679,
						"y": 1512,
						"w": 337,
						"h": 293
					},
					"anchor": {
						"x": 0.5,
						"y": 1
					}
				},
				{
					"filename": "walk/pc10026.png",
					"rotated": false,
					"trimmed": false,
					"sourceSize": {
						"w": 337,
						"h": 293
					},
					"spriteSourceSize": {
						"x": 0,
						"y": 0,
						"w": 337,
						"h": 293
					},
					"frame": {
						"x": 1018,
						"y": 1512,
						"w": 337,
						"h": 293
					},
					"anchor": {
						"x": 0.5,
						"y": 1
					}
				},
				{
					"filename": "walk/pc10027.png",
					"rotated": false,
					"trimmed": false,
					"sourceSize": {
						"w": 337,
						"h": 293
					},
					"spriteSourceSize": {
						"x": 0,
						"y": 0,
						"w": 337,
						"h": 293
					},
					"frame": {
						"x": 1357,
						"y": 1512,
						"w": 337,
						"h": 293
					},
					"anchor": {
						"x": 0.5,
						"y": 1
					}
				},
				{
					"filename": "stairsup/pc10105.png",
					"rotated": false,
					"trimmed": false,
					"sourceSize": {
						"w": 332,
						"h": 329
					},
					"spriteSourceSize": {
						"x": 0,
						"y": 0,
						"w": 332,
						"h": 329
					},
					"frame": {
						"x": 1696,
						"y": 1656,
						"w": 332,
						"h": 329
					},
					"anchor": {
						"x": 0.5,
						"y": 1
					}
				},
				{
					"filename": "hide/pc10047.png",
					"rotated": false,
					"trimmed": false,
					"sourceSize": {
						"w": 312,
						"h": 242
					},
					"spriteSourceSize": {
						"x": 0,
						"y": 0,
						"w": 312,
						"h": 242
					},
					"frame": {
						"x": 1,
						"y": 1789,
						"w": 312,
						"h": 242
					},
					"anchor": {
						"x": 0.5,
						"y": 1
					}
				}
			]
		}
	],
	"meta": {
		"app": "https://www.codeandweb.com/texturepacker",
		"version": "3.0",
		"smartupdate": "$TexturePacker:SmartUpdate:af5c5b931ec0391661e97196ba033db9:c1880782967e7d001752d3680cf4eecc:b083eb5e5cd09ef8985ad50b2b08c5e5$"
	}
}
